PytorchShenduXuexiShiyongZhinanChuyi/README.md
PytorchShenduXuexiShiyongZhinanChuyi/__init__.py
PytorchShenduXuexiShiyongZhinanChuyi/__main__.py
PytorchShenduXuexiShiyongZhinanChuyi/file.epub
PytorchShenduXuexiShiyongZhinanChuyi/index.html
PytorchShenduXuexiShiyongZhinanChuyi/css/__init__.py
PytorchShenduXuexiShiyongZhinanChuyi/css/annotations.css
PytorchShenduXuexiShiyongZhinanChuyi/css/main.css
PytorchShenduXuexiShiyongZhinanChuyi/css/normalize.css
PytorchShenduXuexiShiyongZhinanChuyi/css/popup.css
PytorchShenduXuexiShiyongZhinanChuyi/font/__init__.py
PytorchShenduXuexiShiyongZhinanChuyi/font/fontello.eot
PytorchShenduXuexiShiyongZhinanChuyi/font/fontello.svg
PytorchShenduXuexiShiyongZhinanChuyi/font/fontello.ttf
PytorchShenduXuexiShiyongZhinanChuyi/font/fontello.woff
PytorchShenduXuexiShiyongZhinanChuyi/img/__init__.py
PytorchShenduXuexiShiyongZhinanChuyi/img/annotator-glyph-sprite.png
PytorchShenduXuexiShiyongZhinanChuyi/img/annotator-icon-sprite.png
PytorchShenduXuexiShiyongZhinanChuyi/img/apple-touch-icon.png
PytorchShenduXuexiShiyongZhinanChuyi/img/cancelfullscreen.png
PytorchShenduXuexiShiyongZhinanChuyi/img/close.png
PytorchShenduXuexiShiyongZhinanChuyi/img/fullscreen.png
PytorchShenduXuexiShiyongZhinanChuyi/img/loader.gif
PytorchShenduXuexiShiyongZhinanChuyi/img/menu-icon.png
PytorchShenduXuexiShiyongZhinanChuyi/img/save.png
PytorchShenduXuexiShiyongZhinanChuyi/img/saved.png
PytorchShenduXuexiShiyongZhinanChuyi/img/settings-s.png
PytorchShenduXuexiShiyongZhinanChuyi/img/settings.png
PytorchShenduXuexiShiyongZhinanChuyi/img/star.png
PytorchShenduXuexiShiyongZhinanChuyi/js/__init__.py
PytorchShenduXuexiShiyongZhinanChuyi/js/epub.js
PytorchShenduXuexiShiyongZhinanChuyi/js/epub.min.js
PytorchShenduXuexiShiyongZhinanChuyi/js/epub.min.map
PytorchShenduXuexiShiyongZhinanChuyi/js/hooks.min.js
PytorchShenduXuexiShiyongZhinanChuyi/js/hooks.min.map
PytorchShenduXuexiShiyongZhinanChuyi/js/reader.js
PytorchShenduXuexiShiyongZhinanChuyi/js/reader.js.map
pytorch_shendu_xuexi_shiyong_zhinan_chuyi-2024.3.6.0.dist-info/METADATA
pytorch_shendu_xuexi_shiyong_zhinan_chuyi-2024.3.6.0.dist-info/WHEEL
pytorch_shendu_xuexi_shiyong_zhinan_chuyi-2024.3.6.0.dist-info/entry_points.txt
pytorch_shendu_xuexi_shiyong_zhinan_chuyi-2024.3.6.0.dist-info/top_level.txt
pytorch_shendu_xuexi_shiyong_zhinan_chuyi-2024.3.6.0.dist-info/RECORD
